{
  "instructions": [
    {
      "tick": 0,
      "type": "add-peer",
      "configuration": {
        "address": "mitosis/v1/signal/mock",
        "roles": [
          "signal"
        ]
      }
    },
    {
      "tick": 0,
      "type": "add-peer",
      "configuration": {
        "address": "mitosis/v1/alice/mock",
        "signal": "mitosis/v1/signal/mock"
      }
    },
    {
      "tick": 0,
      "type": "remove-peer",
      "configuration": {
        "address": "mitosis/v1/alice/mock"
      }
    },
    {
      "tick": 0,
      "type": "add-peer",
      "configuration": {
        "address": "mitosis/v1/bob/mock",
        "signal": "mitosis/v1/signal/mock"
      }
    }
  ]
}
